dbmarkenfarben/__init__.py
dbmarkenfarben/farben.py
dbmarkenfarben-0.6.5.dist-info/LICENSE
dbmarkenfarben-0.6.5.dist-info/METADATA
dbmarkenfarben-0.6.5.dist-info/WHEEL
dbmarkenfarben-0.6.5.dist-info/top_level.txt
dbmarkenfarben-0.6.5.dist-info/RECORD
