Metadata-Version: 2.1
Name: dbmarkenfarben
Version: 0.6.5
Summary: Get the html or rgb code of one of the Deutsche Bahn AG brand colours.
Author: Jonas Bunsen
Author-email: jonas.bunsen@deutschebahn.com
Project-URL: Source, https://github.com/jbnsn/dbmarkenfarben/
Keywords: DeutscheBahn
Classifier: Development Status :: 3 - Alpha
Classifier: Intended Audience :: Developers
Classifier: Topic :: Software Development :: Build Tools
Classifier: License :: OSI Approved :: MIT License
Classifier: Programming Language :: Python :: 3 :: Only
Requires-Python: >=3.7, <4
License-File: LICENSE
